Metadata-Version: 1.0
Name: eros-logger
Version: 0.1
Summary: The funniest joke in the world
Home-page: https://github.com/sagarborse/logger
Author: Sagar Borse
Author-email: sagarborse90@gmail.com
License: MIT
Platform: UNKNOWN
